odoo/addons/website_odoo_debranding/README.rst
odoo/addons/website_odoo_debranding/__init__.py
odoo/addons/website_odoo_debranding/__manifest__.py
odoo/addons/website_odoo_debranding/i18n/website_odoo_debranding.pot
odoo/addons/website_odoo_debranding/readme/CONTRIBUTORS.rst
odoo/addons/website_odoo_debranding/readme/DESCRIPTION.rst
odoo/addons/website_odoo_debranding/readme/USAGE.rst
odoo/addons/website_odoo_debranding/static/description/icon.png
odoo/addons/website_odoo_debranding/static/description/index.html
odoo/addons/website_odoo_debranding/templates/disable_odoo.xml
odoo12_addon_website_odoo_debranding-12.0.1.0.0.dist-info/METADATA
odoo12_addon_website_odoo_debranding-12.0.1.0.0.dist-info/RECORD
odoo12_addon_website_odoo_debranding-12.0.1.0.0.dist-info/WHEEL
odoo12_addon_website_odoo_debranding-12.0.1.0.0.dist-info/top_level.txt
